MANIFEST.in
README.rst
setup.py
docs/HISTORY.txt
docs/INSTALL.txt
docs/LICENSE.GPL
docs/LICENSE.txt
redturtle/__init__.py
redturtle.logoswitch.egg-info/PKG-INFO
redturtle.logoswitch.egg-info/SOURCES.txt
redturtle.logoswitch.egg-info/dependency_links.txt
redturtle.logoswitch.egg-info/entry_points.txt
redturtle.logoswitch.egg-info/namespace_packages.txt
redturtle.logoswitch.egg-info/not-zip-safe
redturtle.logoswitch.egg-info/requires.txt
redturtle.logoswitch.egg-info/top_level.txt
redturtle/logoswitch/README.txt
redturtle/logoswitch/__init__.py
redturtle/logoswitch/configure.zcml
redturtle/logoswitch/exportimport.py
redturtle/logoswitch/i18n.sh
redturtle/logoswitch/permissions.zcml
redturtle/logoswitch/testing.py
redturtle/logoswitch/Extensions/install.py
redturtle/logoswitch/browser/__init__.py
redturtle/logoswitch/browser/configure.zcml
redturtle/logoswitch/browser/interfaces.py
redturtle/logoswitch/browser/logo.pt
redturtle/logoswitch/browser/logo_viewlet.py
redturtle/logoswitch/browser/logoswitch.css
redturtle/logoswitch/browser/select_logo.pt
redturtle/logoswitch/browser/select_logo.py
redturtle/logoswitch/locales/redturtle.logoswitch.pot
redturtle/logoswitch/locales/it/LC_MESSAGES/redturtle.logoswitch.mo
redturtle/logoswitch/locales/it/LC_MESSAGES/redturtle.logoswitch.po
redturtle/logoswitch/profiles/default/browserlayer.xml
redturtle/logoswitch/profiles/default/cssregistry.xml
redturtle/logoswitch/profiles/default/metadata.xml
redturtle/logoswitch/profiles/default/redturtle.logoswitch_various.txt
redturtle/logoswitch/profiles/default/skins.xml
redturtle/logoswitch/profiles/uninstall/browserlayer.xml
redturtle/logoswitch/profiles/uninstall/cssregistry.xml
redturtle/logoswitch/profiles/uninstall/skins.xml
redturtle/logoswitch/tests/__init__.py
redturtle/logoswitch/tests/base.py
redturtle/logoswitch/tests/ploneit_logo.png
redturtle/logoswitch/tests/redturtle_logo.jpg
redturtle/logoswitch/tests/test_changelogo.py
redturtle/logoswitch/tests/test_configuration.py