Metadata-Version: 1.1
Name: redturtle.logoswitch
Version: 1.1.0
Summary: Allows users to change plone portal logo from a given images list
Home-page: http://svn.plone.org/svn/plone/products/redturtle.logoswitch
Author: RedTurtle Technology
Author-email: sviluppoplone@redturtle.it
License: GPL
Platform: UNKNOWN
Classifier: Framework :: Plone
Classifier: Framework :: Plone :: 3.3
Classifier: Framework :: Plone :: 4.0
Classifier: Framework :: Plone :: 4.1
Classifier: Framework :: Plone :: 4.2
Classifier: Programming Language :: Python
Classifier: Intended Audience :: Developers
Classifier: Topic :: Software Development :: Libraries :: Python Modules
Classifier: License :: OSI Approved :: GNU General Public License (GPL)
